Metadata-Version: 2.1
Name: pro-video-ferramentas-anderson
Version: 1.0
Summary: Este pacote irá fornecer ferramentas de processamento de vídeo
Home-page: UNKNOWN
Author: Anderson
Author-email: teste@test.com.br
License: UNKNOWN
Keywords: camera,video,processamento
Platform: UNKNOWN
License-File: license.txt
